mdxnet/__init__.py
mdxnet/main.py
mdxnet-1.1.0.dist-info/LICENSE
mdxnet-1.1.0.dist-info/METADATA
mdxnet-1.1.0.dist-info/WHEEL
mdxnet-1.1.0.dist-info/top_level.txt
mdxnet-1.1.0.dist-info/RECORD
