Metadata-Version: 2.2
Name: mdxnet
Version: 1.1.0
Summary: Ultimate Vocal Remover using MDX Net
Home-page: https://github.com/theneodev/mdxnet
Author: Your Name
Author-email: 
Classifier: Programming Language :: Python :: 3
Classifier: License :: OSI Approved :: MIT License
Classifier: Operating System :: OS Independent
Requires-Python: >=3.7
License-File: LICENSE
Requires-Dist: numpy
Requires-Dist: librosa
Requires-Dist: soundfile
Requires-Dist: torch
Requires-Dist: onnxruntime
Requires-Dist: tqdm
Dynamic: author
Dynamic: classifier
Dynamic: description
Dynamic: description-content-type
Dynamic: home-page
Dynamic: requires-dist
Dynamic: requires-python
Dynamic: summary
